storygenerator/__init__.py
storygenerator/evaluation.py
storygenerator/gemini_client.py
storygenerator/generator.py
storygenerator/models.py
storygenerator/prompt_improver.py
storygenerator/prompts.py
storygenerator/py.typed
storygenerator/statistics_tracker.py
storygenerator/types.py
storygenerator/prompt_templates/story_outline_prompt.txt
storygenerator/prompt_templates/story_page_prompt.txt
storygenerator-0.1.1.data/data/prompt_templates/story_outline_prompt.txt
storygenerator-0.1.1.data/data/prompt_templates/story_page_prompt.txt
storygenerator-0.1.1.dist-info/METADATA
storygenerator-0.1.1.dist-info/WHEEL
storygenerator-0.1.1.dist-info/RECORD
